{
"type": "FeatureCollection",
"name": "tambon1",
"crs": { "type": "name", "properties": { "name": "urn:ogc:def:crs:OGC:1.3:CRS84" } },
"features": [
{ "type": "Feature", "properties": { "Shape_Leng": 0.34361226288000002, "Shape_Area": 0.00522836522, "ADM3_EN": "Chan Dum", "ADM3_TH": "จันดุม", "ADM3_PCODE": "TH311501", "ADM3_REF": null, "ADM3ALT1EN": null, "ADM3ALT2EN": null, "ADM3ALT1TH": null, "ADM3ALT2TH": null, "ADM2_EN": "Phlapphla Chai", "ADM2_TH": "พลับพลาชัย", "ADM2_PCODE": "TH3115", "ADM1_EN": "Buri Ram", "ADM1_TH": "บุรีรัมย์", "ADM1_PCODE": "TH31", "ADM0_EN": "Thailand", "ADM0_TH": "ประเทศไทย", "ADM0_PCODE": "TH", "date": "2019-02-18", "validOn": "2022-01-22", "validTo": null }, "geometry": { "type": "MultiPolygon", "coordinates": [ [ [ [ 103.192887, 14.681625 ], [ 103.159722, 14.664192 ], [ 103.164277, 14.628059 ], [ 103.14874, 14.624221 ], [ 103.114256, 14.649675 ], [ 103.095927, 14.649082 ], [ 103.093466, 14.682874 ], [ 103.109988, 14.713317 ], [ 103.176111, 14.701845 ], [ 103.192887, 14.681625 ], [ 103.192887, 14.681625 ] ] ] ] } },
{ "type": "Feature", "properties": { "Shape_Leng": 0.41348964053999998, "Shape_Area": 0.00450173976, "ADM3_EN": "Khok Khamin", "ADM3_TH": "โคกขมิ้น", "ADM3_PCODE": "TH311502", "ADM3_REF": null, "ADM3ALT1EN": null, "ADM3ALT2EN": null, "ADM3ALT1TH": null, "ADM3ALT2TH": null, "ADM2_EN": "Phlapphla Chai", "ADM2_TH": "พลับพลาชัย", "ADM2_PCODE": "TH3115", "ADM1_EN": "Buri Ram", "ADM1_TH": "บุรีรัมย์", "ADM1_PCODE": "TH31", "ADM0_EN": "Thailand", "ADM0_TH": "ประเทศไทย", "ADM0_PCODE": "TH", "date": "2019-02-18", "validOn": "2022-01-22", "validTo": null }, "geometry": { "type": "MultiPolygon", "coordinates": [ [ [ [ 103.210631, 14.7919 ], [ 103.23563, 14.787599 ], [ 103.256739, 14.767239 ], [ 103.224309, 14.747778 ], [ 103.199852, 14.748371 ], [ 103.194481, 14.737414 ], [ 103.148311, 14.744811 ], [ 103.142819, 14.778494 ], [ 103.146721, 14.803532 ], [ 103.171823, 14.787595 ], [ 103.210631, 14.7919 ], [ 103.210631, 14.7919 ] ] ] ] } },
{ "type": "Feature", "properties": { "Shape_Leng": 0.42148612823999998, "Shape_Area": 0.00398009136, "ADM3_EN": "Pa Chan", "ADM3_TH": "ป่าชัน", "ADM3_PCODE": "TH311503", "ADM3_REF": null, "ADM3ALT1EN": null, "ADM3ALT2EN": null, "ADM3ALT1TH": null, "ADM3ALT2TH": null, "ADM2_EN": "Phlapphla Chai", "ADM2_TH": "พลับพลาชัย", "ADM2_PCODE": "TH3115", "ADM1_EN": "Buri Ram", "ADM1_TH": "บุรีรัมย์", "ADM1_PCODE": "TH31", "ADM0_EN": "Thailand", "ADM0_TH": "ประเทศไทย", "ADM0_PCODE": "TH", "date": "2019-02-18", "validOn": "2022-01-22", "validTo": null }, "geometry": { "type": "MultiPolygon", "coordinates": [ [ [ [ 103.266293, 14.766658 ], [ 103.274984, 14.749877 ], [ 103.269434, 14.706321 ], [ 103.260476, 14.683136 ], [ 103.225469, 14.685574 ], [ 103.200466, 14.70097 ], [ 103.223731, 14.734398 ], [ 103.227778, 14.752861 ], [ 103.266293, 14.766658 ], [ 103.266293, 14.766658 ] ] ] ] } },
{ "type": "Feature", "properties": { "Shape_Leng": 0.43477906647999998, "Shape_Area": 0.00437703116, "ADM3_EN": "Sadao", "ADM3_TH": "สะเดา", "ADM3_PCODE": "TH311504", "ADM3_REF": null, "ADM3ALT1EN": null, "ADM3ALT2EN": null, "ADM3ALT1TH": null, "ADM3ALT2TH": null, "ADM2_EN": "Phlapphla Chai", "ADM2_TH": "พลับพลาชัย", "ADM2_PCODE": "TH3115", "ADM1_EN": "Buri Ram", "ADM1_TH": "บุรีรัมย์", "ADM1_PCODE": "TH31", "ADM0_EN": "Thailand", "ADM0_TH": "ประเทศไทย", "ADM0_PCODE": "TH", "date": "2019-02-18", "validOn": "2022-01-22", "validTo": null }, "geometry": { "type": "MultiPolygon", "coordinates": [ [ [ [ 103.216534, 14.750384 ], [ 103.225839, 14.744812 ], [ 103.192887, 14.681625 ], [ 103.176111, 14.701845 ], [ 103.109988, 14.713317 ], [ 103.110556, 14.745005 ], [ 103.146085, 14.745516 ], [ 103.194481, 14.737414 ], [ 103.216534, 14.750384 ], [ 103.216534, 14.750384 ] ] ] ] } },
{ "type": "Feature", "properties": { "Shape_Leng": 0.33389558851000001, "Shape_Area": 0.00448695442, "ADM3_EN": "Samrong", "ADM3_TH": "สำโรง", "ADM3_PCODE": "TH311505", "ADM3_REF": null, "ADM3ALT1EN": null, "ADM3ALT2EN": null, "ADM3ALT1TH": null, "ADM3ALT2TH": null, "ADM2_EN": "Phlapphla Chai", "ADM2_TH": "พลับพลาชัย", "ADM2_PCODE": "TH3115", "ADM1_EN": "Buri Ram", "ADM1_TH": "บุรีรัมย์", "ADM1_PCODE": "TH31", "ADM0_EN": "Thailand", "ADM0_TH": "ประเทศไทย", "ADM0_PCODE": "TH", "date": "2019-02-18", "validOn": "2022-01-22", "validTo": null }, "geometry": { "type": "MultiPolygon", "coordinates": [ [ [ [ 103.112549, 14.811403 ], [ 103.146721, 14.803532 ], [ 103.142819, 14.778494 ], [ 103.148177, 14.746531 ], [ 103.081977, 14.738889 ], [ 103.073107, 14.745769 ], [ 103.084903, 14.76025 ], [ 103.081289, 14.77881 ], [ 103.089583, 14.796794 ], [ 103.077596, 14.800544 ], [ 103.087388, 14.821924 ], [ 103.112549, 14.811403 ], [ 103.112549, 14.811403 ] ] ] ] } }
]
}
