{
"type": "FeatureCollection",
"name": "tambon1",
"crs": { "type": "name", "properties": { "name": "urn:ogc:def:crs:OGC:1.3:CRS84" } },
"features": [
{ "type": "Feature", "properties": { "Shape_Leng": 0.35216644331000002, "Shape_Area": 0.00465046926, "ADM3_EN": "Khu Mueang", "ADM3_TH": "คูเมือง", "ADM3_PCODE": "TH310201", "ADM3_REF": null, "ADM3ALT1EN": null, "ADM3ALT2EN": null, "ADM3ALT1TH": null, "ADM3ALT2TH": null, "ADM2_EN": "Khu Mueang", "ADM2_TH": "คูเมือง", "ADM2_PCODE": "TH3102", "ADM1_EN": "Buri Ram", "ADM1_TH": "บุรีรัมย์", "ADM1_PCODE": "TH31", "ADM0_EN": "Thailand", "ADM0_TH": "ประเทศไทย", "ADM0_PCODE": "TH", "date": "2019-02-18", "validOn": "2022-01-22", "validTo": null }, "geometry": { "type": "MultiPolygon", "coordinates": [ [ [ [ 102.99448, 15.280808 ], [ 103.010195, 15.280272 ], [ 103.012346, 15.251488 ], [ 103.043584, 15.215344 ], [ 103.007986, 15.216521 ], [ 103.004834, 15.201424 ], [ 102.986418, 15.198214 ], [ 102.959016, 15.219466 ], [ 102.959899, 15.279469 ], [ 102.99448, 15.280808 ], [ 102.99448, 15.280808 ] ] ] ] } },
{ "type": "Feature", "properties": { "Shape_Leng": 0.52503639168000005, "Shape_Area": 0.00629905268, "ADM3_EN": "Pakhiap", "ADM3_TH": "ปะเคียบ", "ADM3_PCODE": "TH310202", "ADM3_REF": null, "ADM3ALT1EN": null, "ADM3ALT2EN": null, "ADM3ALT1TH": null, "ADM3ALT2TH": null, "ADM2_EN": "Khu Mueang", "ADM2_TH": "คูเมือง", "ADM2_PCODE": "TH3102", "ADM1_EN": "Buri Ram", "ADM1_TH": "บุรีรัมย์", "ADM1_PCODE": "TH31", "ADM0_EN": "Thailand", "ADM0_TH": "ประเทศไทย", "ADM0_PCODE": "TH", "date": "2019-02-18", "validOn": "2022-01-22", "validTo": null }, "geometry": { "type": "MultiPolygon", "coordinates": [ [ [ [ 103.054822, 15.438072 ], [ 103.085377, 15.427019 ], [ 103.106665, 15.409391 ], [ 103.101692, 15.387721 ], [ 103.085086, 15.382624 ], [ 103.063836, 15.360404 ], [ 103.047711, 15.306824 ], [ 103.03695, 15.31102 ], [ 103.036734, 15.34059 ], [ 103.024991, 15.399368 ], [ 103.012867, 15.416788 ], [ 103.012618, 15.435317 ], [ 103.044482, 15.450345 ], [ 103.054822, 15.438072 ], [ 103.054822, 15.438072 ] ] ] ] } },
{ "type": "Feature", "properties": { "Shape_Leng": 0.39619052419, "Shape_Area": 0.00402088151, "ADM3_EN": "Ban Phae", "ADM3_TH": "บ้านแพ", "ADM3_PCODE": "TH310203", "ADM3_REF": null, "ADM3ALT1EN": null, "ADM3ALT2EN": null, "ADM3ALT1TH": null, "ADM3ALT2TH": null, "ADM2_EN": "Khu Mueang", "ADM2_TH": "คูเมือง", "ADM2_PCODE": "TH3102", "ADM1_EN": "Buri Ram", "ADM1_TH": "บุรีรัมย์", "ADM1_PCODE": "TH31", "ADM0_EN": "Thailand", "ADM0_TH": "ประเทศไทย", "ADM0_PCODE": "TH", "date": "2019-02-18", "validOn": "2022-01-22", "validTo": null }, "geometry": { "type": "MultiPolygon", "coordinates": [ [ [ [ 103.012618, 15.435317 ], [ 103.012867, 15.416788 ], [ 103.024991, 15.399368 ], [ 103.02857, 15.374563 ], [ 103.003502, 15.349062 ], [ 102.977412, 15.344071 ], [ 102.986358, 15.373947 ], [ 102.955097, 15.382734 ], [ 102.951783, 15.403832 ], [ 102.978368, 15.416813 ], [ 102.993543, 15.414501 ], [ 103.012618, 15.435317 ], [ 103.012618, 15.435317 ] ] ] ] } },
{ "type": "Feature", "properties": { "Shape_Leng": 0.40952897961000001, "Shape_Area": 0.00449705738, "ADM3_EN": "Phon Samran", "ADM3_TH": "พรสำราญ", "ADM3_PCODE": "TH310204", "ADM3_REF": null, "ADM3ALT1EN": null, "ADM3ALT2EN": null, "ADM3ALT1TH": null, "ADM3ALT2TH": null, "ADM2_EN": "Khu Mueang", "ADM2_TH": "คูเมือง", "ADM2_PCODE": "TH3102", "ADM1_EN": "Buri Ram", "ADM1_TH": "บุรีรัมย์", "ADM1_PCODE": "TH31", "ADM0_EN": "Thailand", "ADM0_TH": "ประเทศไทย", "ADM0_PCODE": "TH", "date": "2019-02-18", "validOn": "2022-01-22", "validTo": null }, "geometry": { "type": "MultiPolygon", "coordinates": [ [ [ [ 103.042495, 15.204619 ], [ 103.061852, 15.204137 ], [ 103.067919, 15.191661 ], [ 103.058342, 15.162856 ], [ 103.036472, 15.152776 ], [ 103.048122, 15.117143 ], [ 103.017393, 15.13449 ], [ 102.983017, 15.112305 ], [ 102.987204, 15.13215 ], [ 103.020258, 15.196324 ], [ 103.004834, 15.201424 ], [ 103.007986, 15.216521 ], [ 103.042495, 15.204619 ], [ 103.042495, 15.204619 ] ] ] ] } },
{ "type": "Feature", "properties": { "Shape_Leng": 0.58376620613999997, "Shape_Area": 0.00658172383, "ADM3_EN": "Hin Lek Fai", "ADM3_TH": "หินเหล็กไฟ", "ADM3_PCODE": "TH310205", "ADM3_REF": null, "ADM3ALT1EN": null, "ADM3ALT2EN": null, "ADM3ALT1TH": null, "ADM3ALT2TH": null, "ADM2_EN": "Khu Mueang", "ADM2_TH": "คูเมือง", "ADM2_PCODE": "TH3102", "ADM1_EN": "Buri Ram", "ADM1_TH": "บุรีรัมย์", "ADM1_PCODE": "TH31", "ADM0_EN": "Thailand", "ADM0_TH": "ประเทศไทย", "ADM0_PCODE": "TH", "date": "2019-02-18", "validOn": "2022-01-22", "validTo": null }, "geometry": { "type": "MultiPolygon", "coordinates": [ [ [ [ 103.03163, 15.280084 ], [ 103.029596, 15.250597 ], [ 103.044212, 15.246723 ], [ 103.059009, 15.26113 ], [ 103.085853, 15.257466 ], [ 103.094734, 15.247525 ], [ 103.089647, 15.200234 ], [ 103.098853, 15.198644 ], [ 103.100079, 15.17492 ], [ 103.089107, 15.169873 ], [ 103.079841, 15.132147 ], [ 103.062564, 15.134392 ], [ 103.048122, 15.117143 ], [ 103.036472, 15.152776 ], [ 103.058342, 15.162856 ], [ 103.067919, 15.191661 ], [ 103.061852, 15.204137 ], [ 103.041666, 15.209981 ], [ 103.040899, 15.223445 ], [ 103.012346, 15.251488 ], [ 103.010195, 15.280272 ], [ 103.03163, 15.280084 ], [ 103.03163, 15.280084 ] ] ] ] } },
{ "type": "Feature", "properties": { "Shape_Leng": 0.36107094019000002, "Shape_Area": 0.00478511713, "ADM3_EN": "Tum Yai", "ADM3_TH": "ตูมใหญ่", "ADM3_PCODE": "TH310206", "ADM3_REF": null, "ADM3ALT1EN": null, "ADM3ALT2EN": null, "ADM3ALT1TH": null, "ADM3ALT2TH": null, "ADM2_EN": "Khu Mueang", "ADM2_TH": "คูเมือง", "ADM2_PCODE": "TH3102", "ADM1_EN": "Buri Ram", "ADM1_TH": "บุรีรัมย์", "ADM1_PCODE": "TH31", "ADM0_EN": "Thailand", "ADM0_TH": "ประเทศไทย", "ADM0_PCODE": "TH", "date": "2019-02-18", "validOn": "2022-01-22", "validTo": null }, "geometry": { "type": "MultiPolygon", "coordinates": [ [ [ [ 103.134781, 15.241653 ], [ 103.128799, 15.203449 ], [ 103.147419, 15.180173 ], [ 103.150956, 15.152391 ], [ 103.124196, 15.137482 ], [ 103.092333, 15.142795 ], [ 103.089107, 15.169873 ], [ 103.100079, 15.17492 ], [ 103.098853, 15.198644 ], [ 103.089647, 15.200234 ], [ 103.094734, 15.247525 ], [ 103.134781, 15.241653 ], [ 103.134781, 15.241653 ] ] ] ] } },
{ "type": "Feature", "properties": { "Shape_Leng": 0.36969049200999998, "Shape_Area": 0.00497187156, "ADM3_EN": "Nong Khaman", "ADM3_TH": "หนองขมาร", "ADM3_PCODE": "TH310207", "ADM3_REF": null, "ADM3ALT1EN": null, "ADM3ALT2EN": null, "ADM3ALT1TH": null, "ADM3ALT2TH": null, "ADM2_EN": "Khu Mueang", "ADM2_TH": "คูเมือง", "ADM2_PCODE": "TH3102", "ADM1_EN": "Buri Ram", "ADM1_TH": "บุรีรัมย์", "ADM1_PCODE": "TH31", "ADM0_EN": "Thailand", "ADM0_TH": "ประเทศไทย", "ADM0_PCODE": "TH", "date": "2019-02-18", "validOn": "2022-01-22", "validTo": null }, "geometry": { "type": "MultiPolygon", "coordinates": [ [ [ [ 103.036573, 15.343854 ], [ 103.03695, 15.31102 ], [ 103.046922, 15.30638 ], [ 103.03163, 15.280084 ], [ 102.987452, 15.283515 ], [ 102.959899, 15.279469 ], [ 102.967879, 15.290939 ], [ 102.952421, 15.314703 ], [ 102.984832, 15.321608 ], [ 102.977412, 15.344071 ], [ 103.003502, 15.349062 ], [ 103.030659, 15.374213 ], [ 103.036573, 15.343854 ], [ 103.036573, 15.343854 ] ] ] ] } }
]
}
