{
"type": "FeatureCollection",
"name": "tambon1",
"crs": { "type": "name", "properties": { "name": "urn:ogc:def:crs:OGC:1.3:CRS84" } },
"features": [
{ "type": "Feature", "properties": { "Shape_Leng": 0.58580616526999996, "Shape_Area": 0.00863926648, "ADM3_EN": "Nong Kung Thap Ma", "ADM3_TH": "หนองกุงทับม้า", "ADM3_PCODE": "TH411001", "ADM3_REF": null, "ADM3ALT1EN": null, "ADM3ALT2EN": null, "ADM3ALT1TH": null, "ADM3ALT2TH": null, "ADM2_EN": "Wang Sam Mo", "ADM2_TH": "วังสามหมอ", "ADM2_PCODE": "TH4110", "ADM1_EN": "Udon Thani", "ADM1_TH": "อุดรธานี", "ADM1_PCODE": "TH41", "ADM0_EN": "Thailand", "ADM0_TH": "ประเทศไทย", "ADM0_PCODE": "TH", "date": "2019-02-18", "validOn": "2022-01-22", "validTo": null }, "geometry": { "type": "MultiPolygon", "coordinates": [ [ [ [ 103.478808, 17.079495 ], [ 103.502026, 17.068623 ], [ 103.524605, 17.071102 ], [ 103.50745, 17.043798 ], [ 103.515426, 17.041405 ], [ 103.519723, 16.997933 ], [ 103.491445, 16.969314 ], [ 103.43624, 16.972027 ], [ 103.438151, 17.005814 ], [ 103.418627, 16.977521 ], [ 103.414428, 17.01558 ], [ 103.43688, 17.05099 ], [ 103.462997, 17.061357 ], [ 103.478808, 17.079495 ], [ 103.478808, 17.079495 ] ] ] ] } },
{ "type": "Feature", "properties": { "Shape_Leng": 0.4491867911, "Shape_Area": 0.00662139832, "ADM3_EN": "Nong Ya Sai", "ADM3_TH": "หนองหญ้าไซ", "ADM3_PCODE": "TH411002", "ADM3_REF": null, "ADM3ALT1EN": null, "ADM3ALT2EN": null, "ADM3ALT1TH": null, "ADM3ALT2TH": null, "ADM2_EN": "Wang Sam Mo", "ADM2_TH": "วังสามหมอ", "ADM2_PCODE": "TH4110", "ADM1_EN": "Udon Thani", "ADM1_TH": "อุดรธานี", "ADM1_PCODE": "TH41", "ADM0_EN": "Thailand", "ADM0_TH": "ประเทศไทย", "ADM0_PCODE": "TH", "date": "2019-02-18", "validOn": "2022-01-22", "validTo": null }, "geometry": { "type": "MultiPolygon", "coordinates": [ [ [ [ 103.358118, 17.017057 ], [ 103.355998, 17.000646 ], [ 103.42255, 16.971382 ], [ 103.415235, 16.948194 ], [ 103.387456, 16.92621 ], [ 103.374763, 16.903219 ], [ 103.350807, 16.92091 ], [ 103.33012, 16.924071 ], [ 103.328013, 16.967112 ], [ 103.317048, 16.979899 ], [ 103.321768, 16.996032 ], [ 103.335578, 16.998647 ], [ 103.348386, 17.018381 ], [ 103.358118, 17.017057 ], [ 103.358118, 17.017057 ] ] ] ] } },
{ "type": "Feature", "properties": { "Shape_Leng": 0.8477624176, "Shape_Area": 0.01720910344, "ADM3_EN": "Bayao", "ADM3_TH": "บะยาว", "ADM3_PCODE": "TH411003", "ADM3_REF": null, "ADM3ALT1EN": null, "ADM3ALT2EN": null, "ADM3ALT1TH": null, "ADM3ALT2TH": null, "ADM2_EN": "Wang Sam Mo", "ADM2_TH": "วังสามหมอ", "ADM2_PCODE": "TH4110", "ADM1_EN": "Udon Thani", "ADM1_TH": "อุดรธานี", "ADM1_PCODE": "TH41", "ADM0_EN": "Thailand", "ADM0_TH": "ประเทศไทย", "ADM0_PCODE": "TH", "date": "2019-02-18", "validOn": "2022-01-22", "validTo": null }, "geometry": { "type": "MultiPolygon", "coordinates": [ [ [ [ 103.41227, 17.189437 ], [ 103.439237, 17.180198 ], [ 103.443071, 17.160244 ], [ 103.459844, 17.144684 ], [ 103.45802, 17.121508 ], [ 103.488906, 17.076795 ], [ 103.469453, 17.075738 ], [ 103.462997, 17.061357 ], [ 103.43688, 17.05099 ], [ 103.414428, 17.01558 ], [ 103.415427, 16.97115 ], [ 103.379238, 16.993205 ], [ 103.355998, 17.000646 ], [ 103.36104, 17.016989 ], [ 103.333736, 17.032386 ], [ 103.331365, 17.046775 ], [ 103.345928, 17.046616 ], [ 103.345125, 17.066516 ], [ 103.360907, 17.10821 ], [ 103.36192, 17.13313 ], [ 103.375503, 17.130886 ], [ 103.372818, 17.152702 ], [ 103.403655, 17.172189 ], [ 103.41227, 17.189437 ], [ 103.41227, 17.189437 ] ] ] ] } },
{ "type": "Feature", "properties": { "Shape_Leng": 1.0528744859500001, "Shape_Area": 0.02008300624, "ADM3_EN": "Pha Suk", "ADM3_TH": "ผาสุก", "ADM3_PCODE": "TH411004", "ADM3_REF": null, "ADM3ALT1EN": null, "ADM3ALT2EN": null, "ADM3ALT1TH": null, "ADM3ALT2TH": null, "ADM2_EN": "Wang Sam Mo", "ADM2_TH": "วังสามหมอ", "ADM2_PCODE": "TH4110", "ADM1_EN": "Udon Thani", "ADM1_TH": "อุดรธานี", "ADM1_PCODE": "TH41", "ADM0_EN": "Thailand", "ADM0_TH": "ประเทศไทย", "ADM0_PCODE": "TH", "date": "2019-02-18", "validOn": "2022-01-22", "validTo": null }, "geometry": { "type": "MultiPolygon", "coordinates": [ [ [ [ 103.475071, 17.217499 ], [ 103.532273, 17.185794 ], [ 103.572645, 17.157303 ], [ 103.599378, 17.170053 ], [ 103.620224, 17.150723 ], [ 103.638446, 17.11145 ], [ 103.668069, 17.105884 ], [ 103.654079, 17.071423 ], [ 103.666377, 17.054064 ], [ 103.66212, 17.019615 ], [ 103.647231, 17.023474 ], [ 103.652798, 17.047703 ], [ 103.620743, 17.092853 ], [ 103.548355, 17.088985 ], [ 103.536854, 17.06561 ], [ 103.502026, 17.068623 ], [ 103.469511, 17.102437 ], [ 103.45802, 17.121508 ], [ 103.459844, 17.144684 ], [ 103.443071, 17.160244 ], [ 103.439237, 17.180198 ], [ 103.411197, 17.192758 ], [ 103.447192, 17.21734 ], [ 103.475071, 17.217499 ], [ 103.475071, 17.217499 ] ] ] ] } },
{ "type": "Feature", "properties": { "Shape_Leng": 0.44339744913000001, "Shape_Area": 0.00576866905, "ADM3_EN": "Kham Khok Sung", "ADM3_TH": "คำโคกสูง", "ADM3_PCODE": "TH411005", "ADM3_REF": null, "ADM3ALT1EN": null, "ADM3ALT2EN": null, "ADM3ALT1TH": null, "ADM3ALT2TH": null, "ADM2_EN": "Wang Sam Mo", "ADM2_TH": "วังสามหมอ", "ADM2_PCODE": "TH4110", "ADM1_EN": "Udon Thani", "ADM1_TH": "อุดรธานี", "ADM1_PCODE": "TH41", "ADM0_EN": "Thailand", "ADM0_TH": "ประเทศไทย", "ADM0_PCODE": "TH", "date": "2019-02-18", "validOn": "2022-01-22", "validTo": null }, "geometry": { "type": "MultiPolygon", "coordinates": [ [ [ [ 103.411317, 16.943496 ], [ 103.413247, 16.930441 ], [ 103.453211, 16.91314 ], [ 103.470049, 16.878112 ], [ 103.44322, 16.847351 ], [ 103.449729, 16.834482 ], [ 103.421625, 16.803074 ], [ 103.40819, 16.850747 ], [ 103.410692, 16.871491 ], [ 103.380198, 16.906295 ], [ 103.387456, 16.92621 ], [ 103.411317, 16.943496 ], [ 103.411317, 16.943496 ] ] ] ] } },
{ "type": "Feature", "properties": { "Shape_Leng": 0.45532337567999998, "Shape_Area": 0.0051481839, "ADM3_EN": "Wang Sam Mo", "ADM3_TH": "วังสามหมอ", "ADM3_PCODE": "TH411006", "ADM3_REF": null, "ADM3ALT1EN": null, "ADM3ALT2EN": null, "ADM3ALT1TH": null, "ADM3ALT2TH": null, "ADM2_EN": "Wang Sam Mo", "ADM2_TH": "วังสามหมอ", "ADM2_PCODE": "TH4110", "ADM1_EN": "Udon Thani", "ADM1_TH": "อุดรธานี", "ADM1_PCODE": "TH41", "ADM0_EN": "Thailand", "ADM0_TH": "ประเทศไทย", "ADM0_PCODE": "TH", "date": "2019-02-18", "validOn": "2022-01-22", "validTo": null }, "geometry": { "type": "MultiPolygon", "coordinates": [ [ [ [ 103.437974, 16.998861 ], [ 103.43624, 16.972027 ], [ 103.497016, 16.964061 ], [ 103.486747, 16.940216 ], [ 103.491661, 16.907027 ], [ 103.470049, 16.878112 ], [ 103.453211, 16.91314 ], [ 103.413247, 16.930441 ], [ 103.415723, 16.963291 ], [ 103.42569, 16.976024 ], [ 103.426413, 16.997512 ], [ 103.437974, 16.998861 ], [ 103.437974, 16.998861 ] ] ] ] } }
]
}
