{
"type": "FeatureCollection",
"name": "tambon1",
"crs": { "type": "name", "properties": { "name": "urn:ogc:def:crs:OGC:1.3:CRS84" } },
"features": [
{ "type": "Feature", "properties": { "Shape_Leng": 0.16831841466, "Shape_Area": 0.00080932157, "ADM3_EN": "Nai Mueang", "ADM3_TH": "ในเมือง", "ADM3_PCODE": "TH350101", "ADM3_REF": null, "ADM3ALT1EN": null, "ADM3ALT2EN": null, "ADM3ALT1TH": null, "ADM3ALT2TH": null, "ADM2_EN": "Mueang Yasothon", "ADM2_TH": "เมืองยโสธร", "ADM2_PCODE": "TH3501", "ADM1_EN": "Yasothon", "ADM1_TH": "ยโสธร", "ADM1_PCODE": "TH35", "ADM0_EN": "Thailand", "ADM0_TH": "ประเทศไทย", "ADM0_PCODE": "TH", "date": "2019-02-18", "validOn": "2022-01-22", "validTo": null }, "geometry": { "type": "MultiPolygon", "coordinates": [ [ [ [ 104.160634, 15.801099 ], [ 104.155143, 15.778354 ], [ 104.137826, 15.782807 ], [ 104.132483, 15.818406 ], [ 104.160706, 15.811882 ], [ 104.160634, 15.801099 ], [ 104.160634, 15.801099 ] ] ] ] } },
{ "type": "Feature", "properties": { "Shape_Leng": 0.28496707004, "Shape_Area": 0.00272471346, "ADM3_EN": "Nam Kham Yai", "ADM3_TH": "น้ำคำใหญ่", "ADM3_PCODE": "TH350102", "ADM3_REF": null, "ADM3ALT1EN": null, "ADM3ALT2EN": null, "ADM3ALT1TH": null, "ADM3ALT2TH": null, "ADM2_EN": "Mueang Yasothon", "ADM2_TH": "เมืองยโสธร", "ADM2_PCODE": "TH3501", "ADM1_EN": "Yasothon", "ADM1_TH": "ยโสธร", "ADM1_PCODE": "TH35", "ADM0_EN": "Thailand", "ADM0_TH": "ประเทศไทย", "ADM0_PCODE": "TH", "date": "2019-02-18", "validOn": "2022-01-22", "validTo": null }, "geometry": { "type": "MultiPolygon", "coordinates": [ [ [ [ 104.180687, 15.847629 ], [ 104.194593, 15.834534 ], [ 104.207245, 15.807399 ], [ 104.185881, 15.809809 ], [ 104.170664, 15.795365 ], [ 104.160706, 15.811882 ], [ 104.132483, 15.818406 ], [ 104.128934, 15.828576 ], [ 104.140524, 15.859743 ], [ 104.180687, 15.847629 ], [ 104.180687, 15.847629 ] ] ] ] } },
{ "type": "Feature", "properties": { "Shape_Leng": 0.36660039553000001, "Shape_Area": 0.00376671295, "ADM3_EN": "Tat Thong", "ADM3_TH": "ตาดทอง", "ADM3_PCODE": "TH350103", "ADM3_REF": null, "ADM3ALT1EN": null, "ADM3ALT2EN": null, "ADM3ALT1TH": null, "ADM3ALT2TH": null, "ADM2_EN": "Mueang Yasothon", "ADM2_TH": "เมืองยโสธร", "ADM2_PCODE": "TH3501", "ADM1_EN": "Yasothon", "ADM1_TH": "ยโสธร", "ADM1_PCODE": "TH35", "ADM0_EN": "Thailand", "ADM0_TH": "ประเทศไทย", "ADM0_PCODE": "TH", "date": "2019-02-18", "validOn": "2022-01-22", "validTo": null }, "geometry": { "type": "MultiPolygon", "coordinates": [ [ [ [ 104.18707, 15.807926 ], [ 104.224792, 15.804149 ], [ 104.230586, 15.79193 ], [ 104.221792, 15.765443 ], [ 104.25815, 15.751233 ], [ 104.235587, 15.729045 ], [ 104.214492, 15.751201 ], [ 104.18118, 15.756649 ], [ 104.181234, 15.771327 ], [ 104.154728, 15.7844 ], [ 104.156586, 15.799445 ], [ 104.177657, 15.795165 ], [ 104.18707, 15.807926 ], [ 104.18707, 15.807926 ] ] ] ] } },
{ "type": "Feature", "properties": { "Shape_Leng": 0.22887237666, "Shape_Area": 0.00254462485, "ADM3_EN": "Samran", "ADM3_TH": "สำราญ", "ADM3_PCODE": "TH350104", "ADM3_REF": null, "ADM3ALT1EN": null, "ADM3ALT2EN": null, "ADM3ALT1TH": null, "ADM3ALT2TH": null, "ADM2_EN": "Mueang Yasothon", "ADM2_TH": "เมืองยโสธร", "ADM2_PCODE": "TH3501", "ADM1_EN": "Yasothon", "ADM1_TH": "ยโสธร", "ADM1_PCODE": "TH35", "ADM0_EN": "Thailand", "ADM0_TH": "ประเทศไทย", "ADM0_PCODE": "TH", "date": "2019-02-18", "validOn": "2022-01-22", "validTo": null }, "geometry": { "type": "MultiPolygon", "coordinates": [ [ [ [ 104.134796, 15.869647 ], [ 104.140524, 15.859743 ], [ 104.128934, 15.828576 ], [ 104.137323, 15.805232 ], [ 104.11099, 15.806978 ], [ 104.078047, 15.837912 ], [ 104.088055, 15.863277 ], [ 104.123002, 15.863294 ], [ 104.134796, 15.869647 ], [ 104.134796, 15.869647 ] ] ] ] } },
{ "type": "Feature", "properties": { "Shape_Leng": 0.38135093773000001, "Shape_Area": 0.00429279276, "ADM3_EN": "Kho Nuea", "ADM3_TH": "ค้อเหนือ", "ADM3_PCODE": "TH350105", "ADM3_REF": null, "ADM3ALT1EN": null, "ADM3ALT2EN": null, "ADM3ALT1TH": null, "ADM3ALT2TH": null, "ADM2_EN": "Mueang Yasothon", "ADM2_TH": "เมืองยโสธร", "ADM2_PCODE": "TH3501", "ADM1_EN": "Yasothon", "ADM1_TH": "ยโสธร", "ADM1_PCODE": "TH35", "ADM0_EN": "Thailand", "ADM0_TH": "ประเทศไทย", "ADM0_PCODE": "TH", "date": "2019-02-18", "validOn": "2022-01-22", "validTo": null }, "geometry": { "type": "MultiPolygon", "coordinates": [ [ [ [ 104.081669, 15.860233 ], [ 104.087058, 15.851449 ], [ 104.070247, 15.83697 ], [ 104.077264, 15.819122 ], [ 104.033374, 15.796086 ], [ 104.001597, 15.794966 ], [ 104.012216, 15.836702 ], [ 104.029159, 15.859317 ], [ 104.020121, 15.863917 ], [ 104.05345, 15.877586 ], [ 104.081669, 15.860233 ], [ 104.081669, 15.860233 ] ] ] ] } },
{ "type": "Feature", "properties": { "Shape_Leng": 0.38599029038, "Shape_Area": 0.00364096661, "ADM3_EN": "Du Thung", "ADM3_TH": "ดู่ทุ่ง", "ADM3_PCODE": "TH350106", "ADM3_REF": null, "ADM3ALT1EN": null, "ADM3ALT2EN": null, "ADM3ALT1TH": null, "ADM3ALT2TH": null, "ADM2_EN": "Mueang Yasothon", "ADM2_TH": "เมืองยโสธร", "ADM2_PCODE": "TH3501", "ADM1_EN": "Yasothon", "ADM1_TH": "ยโสธร", "ADM1_PCODE": "TH35", "ADM0_EN": "Thailand", "ADM0_TH": "ประเทศไทย", "ADM0_PCODE": "TH", "date": "2019-02-18", "validOn": "2022-01-22", "validTo": null }, "geometry": { "type": "MultiPolygon", "coordinates": [ [ [ [ 104.03588, 15.925634 ], [ 104.046101, 15.923899 ], [ 104.05429, 15.895424 ], [ 104.073736, 15.889868 ], [ 104.087992, 15.908286 ], [ 104.114994, 15.890592 ], [ 104.12314, 15.872624 ], [ 104.115597, 15.861527 ], [ 104.088055, 15.863277 ], [ 104.05345, 15.877586 ], [ 104.036532, 15.869323 ], [ 104.015078, 15.886812 ], [ 104.022411, 15.911166 ], [ 104.03588, 15.925634 ], [ 104.03588, 15.925634 ] ] ] ] } },
{ "type": "Feature", "properties": { "Shape_Leng": 0.43695637928999997, "Shape_Area": 0.00525969884, "ADM3_EN": "Doet", "ADM3_TH": "เดิด", "ADM3_PCODE": "TH350107", "ADM3_REF": null, "ADM3ALT1EN": null, "ADM3ALT2EN": null, "ADM3ALT1TH": null, "ADM3ALT2TH": null, "ADM2_EN": "Mueang Yasothon", "ADM2_TH": "เมืองยโสธร", "ADM2_PCODE": "TH3501", "ADM1_EN": "Yasothon", "ADM1_TH": "ยโสธร", "ADM1_PCODE": "TH35", "ADM0_EN": "Thailand", "ADM0_TH": "ประเทศไทย", "ADM0_PCODE": "TH", "date": "2019-02-18", "validOn": "2022-01-22", "validTo": null }, "geometry": { "type": "MultiPolygon", "coordinates": [ [ [ [ 104.063349, 15.986215 ], [ 104.093995, 15.977306 ], [ 104.101112, 15.958154 ], [ 104.091703, 15.942333 ], [ 104.096546, 15.919722 ], [ 104.073736, 15.889868 ], [ 104.05429, 15.895424 ], [ 104.046101, 15.923899 ], [ 104.032417, 15.926846 ], [ 104.026502, 15.961134 ], [ 104.011232, 15.958113 ], [ 104.036359, 15.984217 ], [ 104.063349, 15.986215 ], [ 104.063349, 15.986215 ] ] ] ] } },
{ "type": "Feature", "properties": { "Shape_Leng": 0.29692151106999998, "Shape_Area": 0.00304394359, "ADM3_EN": "Khan Dai Yai", "ADM3_TH": "ขั้นไดใหญ่", "ADM3_PCODE": "TH350108", "ADM3_REF": null, "ADM3ALT1EN": null, "ADM3ALT2EN": null, "ADM3ALT1TH": null, "ADM3ALT2TH": null, "ADM2_EN": "Mueang Yasothon", "ADM2_TH": "เมืองยโสธร", "ADM2_PCODE": "TH3501", "ADM1_EN": "Yasothon", "ADM1_TH": "ยโสธร", "ADM1_PCODE": "TH35", "ADM0_EN": "Thailand", "ADM0_TH": "ประเทศไทย", "ADM0_PCODE": "TH", "date": "2019-02-18", "validOn": "2022-01-22", "validTo": null }, "geometry": { "type": "MultiPolygon", "coordinates": [ [ [ [ 104.113136, 15.952231 ], [ 104.153282, 15.934099 ], [ 104.148792, 15.914687 ], [ 104.132017, 15.908985 ], [ 104.134657, 15.869828 ], [ 104.123002, 15.863294 ], [ 104.114994, 15.890592 ], [ 104.088011, 15.908305 ], [ 104.096546, 15.919722 ], [ 104.091703, 15.942333 ], [ 104.101148, 15.958181 ], [ 104.113136, 15.952231 ], [ 104.113136, 15.952231 ] ] ] ] } },
{ "type": "Feature", "properties": { "Shape_Leng": 0.27166339374999998, "Shape_Area": 0.00355398598, "ADM3_EN": "Thung Tae", "ADM3_TH": "ทุ่งแต้", "ADM3_PCODE": "TH350109", "ADM3_REF": null, "ADM3ALT1EN": null, "ADM3ALT2EN": null, "ADM3ALT1TH": null, "ADM3ALT2TH": null, "ADM2_EN": "Mueang Yasothon", "ADM2_TH": "เมืองยโสธร", "ADM2_PCODE": "TH3501", "ADM1_EN": "Yasothon", "ADM1_TH": "ยโสธร", "ADM1_PCODE": "TH35", "ADM0_EN": "Thailand", "ADM0_TH": "ประเทศไทย", "ADM0_PCODE": "TH", "date": "2019-02-18", "validOn": "2022-01-22", "validTo": null }, "geometry": { "type": "MultiPolygon", "coordinates": [ [ [ [ 104.168461, 15.951584 ], [ 104.203185, 15.921512 ], [ 104.212548, 15.889133 ], [ 104.194747, 15.864373 ], [ 104.157232, 15.889348 ], [ 104.148673, 15.917158 ], [ 104.1501, 15.939115 ], [ 104.168461, 15.951584 ], [ 104.168461, 15.951584 ] ] ] ] } },
{ "type": "Feature", "properties": { "Shape_Leng": 0.26046894135999998, "Shape_Area": 0.00326440344, "ADM3_EN": "Sing", "ADM3_TH": "สิงห์", "ADM3_PCODE": "TH350110", "ADM3_REF": null, "ADM3ALT1EN": null, "ADM3ALT2EN": null, "ADM3ALT1TH": null, "ADM3ALT2TH": null, "ADM2_EN": "Mueang Yasothon", "ADM2_TH": "เมืองยโสธร", "ADM2_PCODE": "TH3501", "ADM1_EN": "Yasothon", "ADM1_TH": "ยโสธร", "ADM1_PCODE": "TH35", "ADM0_EN": "Thailand", "ADM0_TH": "ประเทศไทย", "ADM0_PCODE": "TH", "date": "2019-02-18", "validOn": "2022-01-22", "validTo": null }, "geometry": { "type": "MultiPolygon", "coordinates": [ [ [ [ 104.282652, 15.825402 ], [ 104.283105, 15.801145 ], [ 104.20809, 15.80454 ], [ 104.195281, 15.833381 ], [ 104.222258, 15.848712 ], [ 104.248857, 15.851634 ], [ 104.282652, 15.825402 ], [ 104.282652, 15.825402 ] ] ] ] } },
{ "type": "Feature", "properties": { "Shape_Leng": 0.29414164195999998, "Shape_Area": 0.00337283655, "ADM3_EN": "Na Samai", "ADM3_TH": "นาสะไมย์", "ADM3_PCODE": "TH350111", "ADM3_REF": null, "ADM3ALT1EN": null, "ADM3ALT2EN": null, "ADM3ALT1TH": null, "ADM3ALT2TH": null, "ADM2_EN": "Mueang Yasothon", "ADM2_TH": "เมืองยโสธร", "ADM2_PCODE": "TH3501", "ADM1_EN": "Yasothon", "ADM1_TH": "ยโสธร", "ADM1_PCODE": "TH35", "ADM0_EN": "Thailand", "ADM0_TH": "ประเทศไทย", "ADM0_PCODE": "TH", "date": "2019-02-18", "validOn": "2022-01-22", "validTo": null }, "geometry": { "type": "MultiPolygon", "coordinates": [ [ [ [ 104.250992, 15.932069 ], [ 104.267998, 15.921283 ], [ 104.270217, 15.907233 ], [ 104.294109, 15.900513 ], [ 104.285954, 15.88779 ], [ 104.27166, 15.894313 ], [ 104.246321, 15.861102 ], [ 104.221001, 15.863736 ], [ 104.223587, 15.882182 ], [ 104.21036, 15.885184 ], [ 104.206754, 15.903233 ], [ 104.225733, 15.923729 ], [ 104.250992, 15.932069 ], [ 104.250992, 15.932069 ] ] ] ] } },
{ "type": "Feature", "properties": { "Shape_Leng": 0.4537731226, "Shape_Area": 0.00442398143, "ADM3_EN": "Khueang Kham", "ADM3_TH": "เขื่องคำ", "ADM3_PCODE": "TH350112", "ADM3_REF": null, "ADM3ALT1EN": null, "ADM3ALT2EN": null, "ADM3ALT1TH": null, "ADM3ALT2TH": null, "ADM2_EN": "Mueang Yasothon", "ADM2_TH": "เมืองยโสธร", "ADM2_PCODE": "TH3501", "ADM1_EN": "Yasothon", "ADM1_TH": "ยโสธร", "ADM1_PCODE": "TH35", "ADM0_EN": "Thailand", "ADM0_TH": "ประเทศไทย", "ADM0_PCODE": "TH", "date": "2019-02-18", "validOn": "2022-01-22", "validTo": null }, "geometry": { "type": "MultiPolygon", "coordinates": [ [ [ [ 104.166042, 15.778614 ], [ 104.181234, 15.771327 ], [ 104.18118, 15.756649 ], [ 104.221606, 15.74375 ], [ 104.191146, 15.737516 ], [ 104.169492, 15.694542 ], [ 104.150695, 15.698612 ], [ 104.127556, 15.719955 ], [ 104.134205, 15.746167 ], [ 104.127713, 15.769804 ], [ 104.137826, 15.782807 ], [ 104.166042, 15.778614 ], [ 104.166042, 15.778614 ] ] ] ] } },
{ "type": "Feature", "properties": { "Shape_Leng": 0.28986573831000001, "Shape_Area": 0.0034368413, "ADM3_EN": "Nong Hin", "ADM3_TH": "หนองหิน", "ADM3_PCODE": "TH350113", "ADM3_REF": null, "ADM3ALT1EN": null, "ADM3ALT2EN": null, "ADM3ALT1TH": null, "ADM3ALT2TH": null, "ADM2_EN": "Mueang Yasothon", "ADM2_TH": "เมืองยโสธร", "ADM2_PCODE": "TH3501", "ADM1_EN": "Yasothon", "ADM1_TH": "ยโสธร", "ADM1_PCODE": "TH35", "ADM0_EN": "Thailand", "ADM0_TH": "ประเทศไทย", "ADM0_PCODE": "TH", "date": "2019-02-18", "validOn": "2022-01-22", "validTo": null }, "geometry": { "type": "MultiPolygon", "coordinates": [ [ [ [ 104.312567, 15.888207 ], [ 104.317559, 15.871295 ], [ 104.303533, 15.847772 ], [ 104.308268, 15.840549 ], [ 104.282652, 15.825402 ], [ 104.261894, 15.83674 ], [ 104.246321, 15.861102 ], [ 104.27166, 15.894313 ], [ 104.285954, 15.88779 ], [ 104.294109, 15.900513 ], [ 104.312567, 15.888207 ], [ 104.312567, 15.888207 ] ] ] ] } },
{ "type": "Feature", "properties": { "Shape_Leng": 0.21246462807, "Shape_Area": 0.0019230318, "ADM3_EN": "Nong Khu", "ADM3_TH": "หนองคู", "ADM3_PCODE": "TH350114", "ADM3_REF": null, "ADM3ALT1EN": null, "ADM3ALT2EN": null, "ADM3ALT1TH": null, "ADM3ALT2TH": null, "ADM2_EN": "Mueang Yasothon", "ADM2_TH": "เมืองยโสธร", "ADM2_PCODE": "TH3501", "ADM1_EN": "Yasothon", "ADM1_TH": "ยโสธร", "ADM1_PCODE": "TH35", "ADM0_EN": "Thailand", "ADM0_TH": "ประเทศไทย", "ADM0_PCODE": "TH", "date": "2019-02-18", "validOn": "2022-01-22", "validTo": null }, "geometry": { "type": "MultiPolygon", "coordinates": [ [ [ [ 104.261406, 15.797493 ], [ 104.283105, 15.801145 ], [ 104.269747, 15.762063 ], [ 104.257719, 15.75692 ], [ 104.221792, 15.765443 ], [ 104.231236, 15.80126 ], [ 104.261406, 15.797493 ], [ 104.261406, 15.797493 ] ] ] ] } },
{ "type": "Feature", "properties": { "Shape_Leng": 0.2706923287, "Shape_Area": 0.00228003803, "ADM3_EN": "Khum Ngoen", "ADM3_TH": "ขุมเงิน", "ADM3_PCODE": "TH350115", "ADM3_REF": null, "ADM3ALT1EN": null, "ADM3ALT2EN": null, "ADM3ALT1TH": null, "ADM3ALT2TH": null, "ADM2_EN": "Mueang Yasothon", "ADM2_TH": "เมืองยโสธร", "ADM2_PCODE": "TH3501", "ADM1_EN": "Yasothon", "ADM1_TH": "ยโสธร", "ADM1_PCODE": "TH35", "ADM0_EN": "Thailand", "ADM0_TH": "ประเทศไทย", "ADM0_PCODE": "TH", "date": "2019-02-18", "validOn": "2022-01-22", "validTo": null }, "geometry": { "type": "MultiPolygon", "coordinates": [ [ [ [ 104.227786, 15.737256 ], [ 104.235587, 15.729045 ], [ 104.210434, 15.70193 ], [ 104.168266, 15.675159 ], [ 104.154809, 15.696442 ], [ 104.169492, 15.694542 ], [ 104.191146, 15.737516 ], [ 104.221606, 15.74375 ], [ 104.227786, 15.737256 ], [ 104.227786, 15.737256 ] ] ] ] } },
{ "type": "Feature", "properties": { "Shape_Leng": 0.21690412621, "Shape_Area": 0.00218860547, "ADM3_EN": "Thung Nang Ok", "ADM3_TH": "ทุ่งนางโอก", "ADM3_PCODE": "TH350116", "ADM3_REF": null, "ADM3ALT1EN": null, "ADM3ALT2EN": null, "ADM3ALT1TH": null, "ADM3ALT2TH": null, "ADM2_EN": "Mueang Yasothon", "ADM2_TH": "เมืองยโสธร", "ADM2_PCODE": "TH3501", "ADM1_EN": "Yasothon", "ADM1_TH": "ยโสธร", "ADM1_PCODE": "TH35", "ADM0_EN": "Thailand", "ADM0_TH": "ประเทศไทย", "ADM0_PCODE": "TH", "date": "2019-02-18", "validOn": "2022-01-22", "validTo": null }, "geometry": { "type": "MultiPolygon", "coordinates": [ [ [ [ 104.138701, 15.914334 ], [ 104.148792, 15.914687 ], [ 104.157232, 15.889348 ], [ 104.194747, 15.864373 ], [ 104.178582, 15.845319 ], [ 104.139711, 15.86054 ], [ 104.131183, 15.874478 ], [ 104.132017, 15.908985 ], [ 104.138701, 15.914334 ], [ 104.138701, 15.914334 ] ] ] ] } },
{ "type": "Feature", "properties": { "Shape_Leng": 0.17591927248, "Shape_Area": 0.00142047379, "ADM3_EN": "Nong Ruea", "ADM3_TH": "หนองเรือ", "ADM3_PCODE": "TH350117", "ADM3_REF": null, "ADM3ALT1EN": null, "ADM3ALT2EN": null, "ADM3ALT1TH": null, "ADM3ALT2TH": null, "ADM2_EN": "Mueang Yasothon", "ADM2_TH": "เมืองยโสธร", "ADM2_PCODE": "TH3501", "ADM1_EN": "Yasothon", "ADM1_TH": "ยโสธร", "ADM1_PCODE": "TH35", "ADM0_EN": "Thailand", "ADM0_TH": "ประเทศไทย", "ADM0_PCODE": "TH", "date": "2019-02-18", "validOn": "2022-01-22", "validTo": null }, "geometry": { "type": "MultiPolygon", "coordinates": [ [ [ [ 104.222382, 15.863168 ], [ 104.222258, 15.848712 ], [ 104.195281, 15.833381 ], [ 104.180687, 15.847629 ], [ 104.210602, 15.884907 ], [ 104.223587, 15.882182 ], [ 104.222382, 15.863168 ], [ 104.222382, 15.863168 ] ] ] ] } },
{ "type": "Feature", "properties": { "Shape_Leng": 0.29334179807, "Shape_Area": 0.00288892733, "ADM3_EN": "Nong Pet", "ADM3_TH": "หนองเป็ด", "ADM3_PCODE": "TH350118", "ADM3_REF": null, "ADM3ALT1EN": null, "ADM3ALT2EN": null, "ADM3ALT1TH": null, "ADM3ALT2TH": null, "ADM2_EN": "Mueang Yasothon", "ADM2_TH": "เมืองยโสธร", "ADM2_PCODE": "TH3501", "ADM1_EN": "Yasothon", "ADM1_TH": "ยโสธร", "ADM1_PCODE": "TH35", "ADM0_EN": "Thailand", "ADM0_TH": "ประเทศไทย", "ADM0_PCODE": "TH", "date": "2019-02-18", "validOn": "2022-01-22", "validTo": null }, "geometry": { "type": "MultiPolygon", "coordinates": [ [ [ [ 104.378237, 15.903436 ], [ 104.354912, 15.882679 ], [ 104.362638, 15.873525 ], [ 104.345953, 15.849205 ], [ 104.308268, 15.840549 ], [ 104.303533, 15.847772 ], [ 104.317559, 15.871295 ], [ 104.310899, 15.893462 ], [ 104.34545, 15.902892 ], [ 104.353432, 15.91417 ], [ 104.378237, 15.903436 ], [ 104.378237, 15.903436 ] ] ] ] } }
]
}
