{
"type": "FeatureCollection",
"name": "tambon1",
"crs": { "type": "name", "properties": { "name": "urn:ogc:def:crs:OGC:1.3:CRS84" } },
"features": [
{ "type": "Feature", "properties": { "Shape_Leng": 0.24284892265, "Shape_Area": 0.00230440288, "ADM3_EN": "Si", "ADM3_TH": "สิ", "ADM3_PCODE": "TH330801", "ADM3_REF": null, "ADM3ALT1EN": null, "ADM3ALT2EN": null, "ADM3ALT1TH": null, "ADM3ALT2TH": null, "ADM2_EN": "Khun Han", "ADM2_TH": "ขุนหาญ", "ADM2_PCODE": "TH3308", "ADM1_EN": "Si Sa Ket", "ADM1_TH": "ศรีสะเกษ", "ADM1_PCODE": "TH33", "ADM0_EN": "Thailand", "ADM0_TH": "ประเทศไทย", "ADM0_PCODE": "TH", "date": "2019-02-18", "validOn": "2022-01-22", "validTo": null }, "geometry": { "type": "MultiPolygon", "coordinates": [ [ [ [ 104.431249, 14.587604 ], [ 104.413781, 14.618364 ], [ 104.41367, 14.641407 ], [ 104.437201, 14.660431 ], [ 104.459184, 14.623745 ], [ 104.446244, 14.590215 ], [ 104.431249, 14.587604 ], [ 104.431249, 14.587604 ] ] ] ] } },
{ "type": "Feature", "properties": { "Shape_Leng": 0.8505073205, "Shape_Area": 0.02480681847, "ADM3_EN": "Bak Dong", "ADM3_TH": "บักดอง", "ADM3_PCODE": "TH330802", "ADM3_REF": null, "ADM3ALT1EN": null, "ADM3ALT2EN": null, "ADM3ALT1TH": null, "ADM3ALT2TH": null, "ADM2_EN": "Khun Han", "ADM2_TH": "ขุนหาญ", "ADM2_PCODE": "TH3308", "ADM1_EN": "Si Sa Ket", "ADM1_TH": "ศรีสะเกษ", "ADM1_PCODE": "TH33", "ADM0_EN": "Thailand", "ADM0_TH": "ประเทศไทย", "ADM0_PCODE": "TH", "date": "2019-02-18", "validOn": "2022-01-22", "validTo": null }, "geometry": { "type": "MultiPolygon", "coordinates": [ [ [ [ 104.456071, 14.58717 ], [ 104.469795, 14.575671 ], [ 104.485548, 14.547351 ], [ 104.53833, 14.55287 ], [ 104.516554, 14.524908 ], [ 104.4927, 14.482249 ], [ 104.506979, 14.452142 ], [ 104.499681, 14.423048 ], [ 104.498249, 14.373394 ], [ 104.483427, 14.366915 ], [ 104.473434, 14.346903 ], [ 104.461791, 14.359475 ], [ 104.436487, 14.357147 ], [ 104.42382, 14.368449 ], [ 104.400323, 14.372747 ], [ 104.346603, 14.368127 ], [ 104.361051, 14.398416 ], [ 104.375113, 14.446466 ], [ 104.391522, 14.456176 ], [ 104.398622, 14.504379 ], [ 104.395124, 14.520604 ], [ 104.423172, 14.558161 ], [ 104.426392, 14.587617 ], [ 104.456071, 14.58717 ], [ 104.456071, 14.58717 ] ] ] ] } },
{ "type": "Feature", "properties": { "Shape_Leng": 0.40900326932999997, "Shape_Area": 0.00676765253, "ADM3_EN": "Phran", "ADM3_TH": "พราน", "ADM3_PCODE": "TH330803", "ADM3_REF": null, "ADM3ALT1EN": null, "ADM3ALT2EN": null, "ADM3ALT1TH": null, "ADM3ALT2TH": null, "ADM2_EN": "Khun Han", "ADM2_TH": "ขุนหาญ", "ADM2_PCODE": "TH3308", "ADM1_EN": "Si Sa Ket", "ADM1_TH": "ศรีสะเกษ", "ADM1_PCODE": "TH33", "ADM0_EN": "Thailand", "ADM0_TH": "ประเทศไทย", "ADM0_PCODE": "TH", "date": "2019-02-18", "validOn": "2022-01-22", "validTo": null }, "geometry": { "type": "MultiPolygon", "coordinates": [ [ [ [ 104.551717, 14.616909 ], [ 104.53461, 14.586349 ], [ 104.53833, 14.55287 ], [ 104.485548, 14.547351 ], [ 104.453002, 14.598623 ], [ 104.459184, 14.623745 ], [ 104.452831, 14.638401 ], [ 104.477744, 14.642747 ], [ 104.489494, 14.628484 ], [ 104.517102, 14.648785 ], [ 104.525163, 14.633796 ], [ 104.551717, 14.616909 ], [ 104.551717, 14.616909 ] ] ] ] } },
{ "type": "Feature", "properties": { "Shape_Leng": 0.20813730136, "Shape_Area": 0.0017985158, "ADM3_EN": "Pho Wong", "ADM3_TH": "โพธิ์วงศ์", "ADM3_PCODE": "TH330804", "ADM3_REF": null, "ADM3ALT1EN": null, "ADM3ALT2EN": null, "ADM3ALT1TH": null, "ADM3ALT2TH": null, "ADM2_EN": "Khun Han", "ADM2_TH": "ขุนหาญ", "ADM2_PCODE": "TH3308", "ADM1_EN": "Si Sa Ket", "ADM1_TH": "ศรีสะเกษ", "ADM1_PCODE": "TH33", "ADM0_EN": "Thailand", "ADM0_TH": "ประเทศไทย", "ADM0_PCODE": "TH", "date": "2019-02-18", "validOn": "2022-01-22", "validTo": null }, "geometry": { "type": "MultiPolygon", "coordinates": [ [ [ [ 104.482084, 14.68076 ], [ 104.473017, 14.67215 ], [ 104.475834, 14.64378 ], [ 104.451391, 14.637907 ], [ 104.425141, 14.676788 ], [ 104.449819, 14.686487 ], [ 104.482084, 14.68076 ], [ 104.482084, 14.68076 ] ] ] ] } },
{ "type": "Feature", "properties": { "Shape_Leng": 0.3321670467, "Shape_Area": 0.00416317422, "ADM3_EN": "Phrai", "ADM3_TH": "ไพร", "ADM3_PCODE": "TH330805", "ADM3_REF": null, "ADM3ALT1EN": null, "ADM3ALT2EN": null, "ADM3ALT1TH": null, "ADM3ALT2TH": null, "ADM2_EN": "Khun Han", "ADM2_TH": "ขุนหาญ", "ADM2_PCODE": "TH3308", "ADM1_EN": "Si Sa Ket", "ADM1_TH": "ศรีสะเกษ", "ADM1_PCODE": "TH33", "ADM0_EN": "Thailand", "ADM0_TH": "ประเทศไทย", "ADM0_PCODE": "TH", "date": "2019-02-18", "validOn": "2022-01-22", "validTo": null }, "geometry": { "type": "MultiPolygon", "coordinates": [ [ [ [ 104.498855, 14.737986 ], [ 104.495388, 14.692588 ], [ 104.487179, 14.684695 ], [ 104.449819, 14.686487 ], [ 104.425948, 14.677315 ], [ 104.415103, 14.686368 ], [ 104.425803, 14.739899 ], [ 104.439011, 14.729619 ], [ 104.488498, 14.749872 ], [ 104.498855, 14.737986 ], [ 104.498855, 14.737986 ] ] ] ] } },
{ "type": "Feature", "properties": { "Shape_Leng": 0.29135725538000001, "Shape_Area": 0.00259144447, "ADM3_EN": "Krawan", "ADM3_TH": "กระหวัน", "ADM3_PCODE": "TH330806", "ADM3_REF": null, "ADM3ALT1EN": null, "ADM3ALT2EN": null, "ADM3ALT1TH": null, "ADM3ALT2TH": null, "ADM2_EN": "Khun Han", "ADM2_TH": "ขุนหาญ", "ADM2_PCODE": "TH3308", "ADM1_EN": "Si Sa Ket", "ADM1_TH": "ศรีสะเกษ", "ADM1_PCODE": "TH33", "ADM0_EN": "Thailand", "ADM0_TH": "ประเทศไทย", "ADM0_PCODE": "TH", "date": "2019-02-18", "validOn": "2022-01-22", "validTo": null }, "geometry": { "type": "MultiPolygon", "coordinates": [ [ [ [ 104.415007, 14.686483 ], [ 104.430544, 14.664921 ], [ 104.426623, 14.650918 ], [ 104.392679, 14.62793 ], [ 104.383187, 14.632978 ], [ 104.382096, 14.662887 ], [ 104.36272, 14.673617 ], [ 104.395655, 14.682917 ], [ 104.420519, 14.707112 ], [ 104.415007, 14.686483 ], [ 104.415007, 14.686483 ] ] ] ] } },
{ "type": "Feature", "properties": { "Shape_Leng": 0.1955680825, "Shape_Area": 0.00163590214, "ADM3_EN": "Khun Han", "ADM3_TH": "ขุนหาญ", "ADM3_PCODE": "TH330807", "ADM3_REF": null, "ADM3ALT1EN": null, "ADM3ALT2EN": null, "ADM3ALT1TH": null, "ADM3ALT2TH": null, "ADM2_EN": "Khun Han", "ADM2_TH": "ขุนหาญ", "ADM2_PCODE": "TH3308", "ADM1_EN": "Si Sa Ket", "ADM1_TH": "ศรีสะเกษ", "ADM1_PCODE": "TH33", "ADM0_EN": "Thailand", "ADM0_TH": "ประเทศไทย", "ADM0_PCODE": "TH", "date": "2019-02-18", "validOn": "2022-01-22", "validTo": null }, "geometry": { "type": "MultiPolygon", "coordinates": [ [ [ [ 104.382265, 14.651084 ], [ 104.392679, 14.62793 ], [ 104.366413, 14.59936 ], [ 104.348027, 14.600341 ], [ 104.357797, 14.640726 ], [ 104.371969, 14.666736 ], [ 104.382265, 14.651084 ], [ 104.382265, 14.651084 ] ] ] ] } },
{ "type": "Feature", "properties": { "Shape_Leng": 0.29808599820999998, "Shape_Area": 0.00308622551, "ADM3_EN": "Non Sung", "ADM3_TH": "โนนสูง", "ADM3_PCODE": "TH330808", "ADM3_REF": null, "ADM3ALT1EN": null, "ADM3ALT2EN": null, "ADM3ALT1TH": null, "ADM3ALT2TH": null, "ADM2_EN": "Khun Han", "ADM2_TH": "ขุนหาญ", "ADM2_PCODE": "TH3308", "ADM1_EN": "Si Sa Ket", "ADM1_TH": "ศรีสะเกษ", "ADM1_PCODE": "TH33", "ADM0_EN": "Thailand", "ADM0_TH": "ประเทศไทย", "ADM0_PCODE": "TH", "date": "2019-02-18", "validOn": "2022-01-22", "validTo": null }, "geometry": { "type": "MultiPolygon", "coordinates": [ [ [ [ 104.41367, 14.641407 ], [ 104.413781, 14.618364 ], [ 104.431648, 14.5808 ], [ 104.423172, 14.558161 ], [ 104.40035, 14.529331 ], [ 104.393549, 14.587801 ], [ 104.376126, 14.593171 ], [ 104.385872, 14.623232 ], [ 104.41367, 14.641407 ], [ 104.41367, 14.641407 ] ] ] ] } },
{ "type": "Feature", "properties": { "Shape_Leng": 0.73291649183999996, "Shape_Area": 0.01361851984, "ADM3_EN": "Kan Throm", "ADM3_TH": "กันทรอม", "ADM3_PCODE": "TH330809", "ADM3_REF": null, "ADM3ALT1EN": null, "ADM3ALT2EN": null, "ADM3ALT1TH": null, "ADM3ALT2TH": null, "ADM2_EN": "Khun Han", "ADM2_TH": "ขุนหาญ", "ADM2_PCODE": "TH3308", "ADM1_EN": "Si Sa Ket", "ADM1_TH": "ศรีสะเกษ", "ADM1_PCODE": "TH33", "ADM0_EN": "Thailand", "ADM0_TH": "ประเทศไทย", "ADM0_PCODE": "TH", "date": "2019-02-18", "validOn": "2022-01-22", "validTo": null }, "geometry": { "type": "MultiPolygon", "coordinates": [ [ [ [ 104.376679, 14.60999 ], [ 104.378026, 14.583488 ], [ 104.387309, 14.576328 ], [ 104.334725, 14.519446 ], [ 104.335977, 14.48791 ], [ 104.309062, 14.425704 ], [ 104.316349, 14.416011 ], [ 104.318857, 14.378591 ], [ 104.307944, 14.382622 ], [ 104.278192, 14.412257 ], [ 104.26167, 14.420182 ], [ 104.263671, 14.437889 ], [ 104.251105, 14.473995 ], [ 104.261688, 14.50928 ], [ 104.288112, 14.516131 ], [ 104.284737, 14.58314 ], [ 104.348027, 14.600341 ], [ 104.366413, 14.59936 ], [ 104.376679, 14.60999 ], [ 104.376679, 14.60999 ] ] ] ] } },
{ "type": "Feature", "properties": { "Shape_Leng": 0.29735546456, "Shape_Area": 0.00399746917, "ADM3_EN": "Phu Fai", "ADM3_TH": "ภูฝ้าย", "ADM3_PCODE": "TH330810", "ADM3_REF": null, "ADM3ALT1EN": null, "ADM3ALT2EN": null, "ADM3ALT1TH": null, "ADM3ALT2TH": null, "ADM2_EN": "Khun Han", "ADM2_TH": "ขุนหาญ", "ADM2_PCODE": "TH3308", "ADM1_EN": "Si Sa Ket", "ADM1_TH": "ศรีสะเกษ", "ADM1_PCODE": "TH33", "ADM0_EN": "Thailand", "ADM0_TH": "ประเทศไทย", "ADM0_PCODE": "TH", "date": "2019-02-18", "validOn": "2022-01-22", "validTo": null }, "geometry": { "type": "MultiPolygon", "coordinates": [ [ [ [ 104.532178, 14.695247 ], [ 104.542507, 14.680991 ], [ 104.529746, 14.655683 ], [ 104.504896, 14.63315 ], [ 104.489494, 14.628484 ], [ 104.475834, 14.64378 ], [ 104.473017, 14.67215 ], [ 104.495388, 14.692588 ], [ 104.498855, 14.737986 ], [ 104.532178, 14.695247 ], [ 104.532178, 14.695247 ] ] ] ] } },
{ "type": "Feature", "properties": { "Shape_Leng": 0.28573398196, "Shape_Area": 0.00412211929, "ADM3_EN": "Pho Krasang", "ADM3_TH": "โพธิ์กระสังข์", "ADM3_PCODE": "TH330811", "ADM3_REF": null, "ADM3ALT1EN": null, "ADM3ALT2EN": null, "ADM3ALT1TH": null, "ADM3ALT2TH": null, "ADM2_EN": "Khun Han", "ADM2_TH": "ขุนหาญ", "ADM2_PCODE": "TH3308", "ADM1_EN": "Si Sa Ket", "ADM1_TH": "ศรีสะเกษ", "ADM1_PCODE": "TH33", "ADM0_EN": "Thailand", "ADM0_TH": "ประเทศไทย", "ADM0_PCODE": "TH", "date": "2019-02-18", "validOn": "2022-01-22", "validTo": null }, "geometry": { "type": "MultiPolygon", "coordinates": [ [ [ [ 104.354, 14.629232 ], [ 104.348027, 14.600341 ], [ 104.284737, 14.58314 ], [ 104.284849, 14.605641 ], [ 104.313338, 14.648453 ], [ 104.36272, 14.673617 ], [ 104.371969, 14.666736 ], [ 104.354, 14.629232 ], [ 104.354, 14.629232 ] ] ] ] } },
{ "type": "Feature", "properties": { "Shape_Leng": 0.60019582413000006, "Shape_Area": 0.01021856102, "ADM3_EN": "Huai Chan", "ADM3_TH": "ห้วยจันทร์", "ADM3_PCODE": "TH330812", "ADM3_REF": null, "ADM3ALT1EN": null, "ADM3ALT2EN": null, "ADM3ALT1TH": null, "ADM3ALT2TH": null, "ADM2_EN": "Khun Han", "ADM2_TH": "ขุนหาญ", "ADM2_PCODE": "TH3308", "ADM1_EN": "Si Sa Ket", "ADM1_TH": "ศรีสะเกษ", "ADM1_PCODE": "TH33", "ADM0_EN": "Thailand", "ADM0_TH": "ประเทศไทย", "ADM0_PCODE": "TH", "date": "2019-02-18", "validOn": "2022-01-22", "validTo": null }, "geometry": { "type": "MultiPolygon", "coordinates": [ [ [ [ 104.394545, 14.560726 ], [ 104.40035, 14.529331 ], [ 104.391675, 14.480523 ], [ 104.391522, 14.456176 ], [ 104.375113, 14.446466 ], [ 104.361051, 14.398416 ], [ 104.346603, 14.368127 ], [ 104.322304, 14.372871 ], [ 104.316349, 14.416011 ], [ 104.309062, 14.425704 ], [ 104.3278, 14.465223 ], [ 104.322385, 14.47687 ], [ 104.335977, 14.48791 ], [ 104.334725, 14.519446 ], [ 104.387309, 14.576328 ], [ 104.377833, 14.592666 ], [ 104.393549, 14.587801 ], [ 104.394545, 14.560726 ], [ 104.394545, 14.560726 ] ] ] ] } }
]
}
