{
"type": "FeatureCollection",
"name": "tambon1",
"crs": { "type": "name", "properties": { "name": "urn:ogc:def:crs:OGC:1.3:CRS84" } },
"features": [
{ "type": "Feature", "properties": { "Shape_Leng": 0.12641244199000001, "Shape_Area": 0.00047163727, "ADM3_EN": "Talat", "ADM3_TH": "ตลาด", "ADM3_PCODE": "TH220101", "ADM3_REF": null, "ADM3ALT1EN": null, "ADM3ALT2EN": null, "ADM3ALT1TH": null, "ADM3ALT2TH": null, "ADM2_EN": "Mueang Chanthaburi", "ADM2_TH": "เมืองจันทบุรี", "ADM2_PCODE": "TH2201", "ADM1_EN": "Chanthaburi", "ADM1_TH": "จันทบุรี", "ADM1_PCODE": "TH22", "ADM0_EN": "Thailand", "ADM0_TH": "ประเทศไทย", "ADM0_PCODE": "TH", "date": "2019-02-18", "validOn": "2022-01-22", "validTo": null }, "geometry": { "type": "MultiPolygon", "coordinates": [ [ [ [ 102.111846, 12.603276 ], [ 102.093192, 12.582062 ], [ 102.08245, 12.598565 ], [ 102.111846, 12.603276 ], [ 102.111846, 12.603276 ] ] ] ] } },
{ "type": "Feature", "properties": { "Shape_Leng": 0.10985435363, "Shape_Area": 0.00038373259, "ADM3_EN": "Wat Mai", "ADM3_TH": "วัดใหม่", "ADM3_PCODE": "TH220102", "ADM3_REF": null, "ADM3ALT1EN": null, "ADM3ALT2EN": null, "ADM3ALT1TH": null, "ADM3ALT2TH": null, "ADM2_EN": "Mueang Chanthaburi", "ADM2_TH": "เมืองจันทบุรี", "ADM2_PCODE": "TH2201", "ADM1_EN": "Chanthaburi", "ADM1_TH": "จันทบุรี", "ADM1_PCODE": "TH22", "ADM0_EN": "Thailand", "ADM0_TH": "ประเทศไทย", "ADM0_PCODE": "TH", "date": "2019-02-18", "validOn": "2022-01-22", "validTo": null }, "geometry": { "type": "MultiPolygon", "coordinates": [ [ [ [ 102.10822, 12.62308 ], [ 102.117627, 12.608398 ], [ 102.096427, 12.595934 ], [ 102.092469, 12.618868 ], [ 102.10822, 12.62308 ], [ 102.10822, 12.62308 ] ] ] ] } },
{ "type": "Feature", "properties": { "Shape_Leng": 0.27674698712000001, "Shape_Area": 0.00234969219, "ADM3_EN": "Khlong Narai", "ADM3_TH": "คลองนารายณ์", "ADM3_PCODE": "TH220103", "ADM3_REF": null, "ADM3ALT1EN": null, "ADM3ALT2EN": null, "ADM3ALT1TH": null, "ADM3ALT2TH": null, "ADM2_EN": "Mueang Chanthaburi", "ADM2_TH": "เมืองจันทบุรี", "ADM2_PCODE": "TH2201", "ADM1_EN": "Chanthaburi", "ADM1_TH": "จันทบุรี", "ADM1_PCODE": "TH22", "ADM0_EN": "Thailand", "ADM0_TH": "ประเทศไทย", "ADM0_PCODE": "TH", "date": "2019-02-18", "validOn": "2022-01-22", "validTo": null }, "geometry": { "type": "MultiPolygon", "coordinates": [ [ [ [ 102.134751, 12.602282 ], [ 102.209034, 12.566825 ], [ 102.205986, 12.551097 ], [ 102.171478, 12.559318 ], [ 102.135282, 12.556899 ], [ 102.1386, 12.58007 ], [ 102.124503, 12.589266 ], [ 102.134751, 12.602282 ], [ 102.134751, 12.602282 ] ] ] ] } },
{ "type": "Feature", "properties": { "Shape_Leng": 0.25873828549, "Shape_Area": 0.00212232194, "ADM3_EN": "Ko Khwang", "ADM3_TH": "เกาะขวาง", "ADM3_PCODE": "TH220104", "ADM3_REF": null, "ADM3ALT1EN": null, "ADM3ALT2EN": null, "ADM3ALT1TH": null, "ADM3ALT2TH": null, "ADM2_EN": "Mueang Chanthaburi", "ADM2_TH": "เมืองจันทบุรี", "ADM2_PCODE": "TH2201", "ADM1_EN": "Chanthaburi", "ADM1_TH": "จันทบุรี", "ADM1_PCODE": "TH22", "ADM0_EN": "Thailand", "ADM0_TH": "ประเทศไทย", "ADM0_PCODE": "TH", "date": "2019-02-18", "validOn": "2022-01-22", "validTo": null }, "geometry": { "type": "MultiPolygon", "coordinates": [ [ [ [ 102.106581, 12.59277 ], [ 102.1386, 12.58007 ], [ 102.1311, 12.564019 ], [ 102.111474, 12.556197 ], [ 102.11216, 12.541975 ], [ 102.096735, 12.549987 ], [ 102.0777, 12.536142 ], [ 102.073839, 12.562613 ], [ 102.083767, 12.58766 ], [ 102.106581, 12.59277 ], [ 102.106581, 12.59277 ] ] ] ] } },
{ "type": "Feature", "properties": { "Shape_Leng": 0.2798982424, "Shape_Area": 0.00251989617, "ADM3_EN": "Kom Bang", "ADM3_TH": "คมบาง", "ADM3_PCODE": "TH220105", "ADM3_REF": null, "ADM3ALT1EN": null, "ADM3ALT2EN": null, "ADM3ALT1TH": null, "ADM3ALT2TH": null, "ADM2_EN": "Mueang Chanthaburi", "ADM2_TH": "เมืองจันทบุรี", "ADM2_PCODE": "TH2201", "ADM1_EN": "Chanthaburi", "ADM1_TH": "จันทบุรี", "ADM1_PCODE": "TH22", "ADM0_EN": "Thailand", "ADM0_TH": "ประเทศไทย", "ADM0_PCODE": "TH", "date": "2019-02-18", "validOn": "2022-01-22", "validTo": null }, "geometry": { "type": "MultiPolygon", "coordinates": [ [ [ [ 102.152819, 12.561599 ], [ 102.205986, 12.551097 ], [ 102.209638, 12.531336 ], [ 102.185058, 12.519468 ], [ 102.160239, 12.528683 ], [ 102.133474, 12.514027 ], [ 102.127327, 12.530878 ], [ 102.139659, 12.559949 ], [ 102.152819, 12.561599 ], [ 102.152819, 12.561599 ] ] ] ] } },
{ "type": "Feature", "properties": { "Shape_Leng": 0.34394174248999998, "Shape_Area": 0.00342548465, "ADM3_EN": "Tha Chang", "ADM3_TH": "ท่าช้าง", "ADM3_PCODE": "TH220106", "ADM3_REF": null, "ADM3ALT1EN": null, "ADM3ALT2EN": null, "ADM3ALT1TH": null, "ADM3ALT2TH": null, "ADM2_EN": "Mueang Chanthaburi", "ADM2_TH": "เมืองจันทบุรี", "ADM2_PCODE": "TH2201", "ADM1_EN": "Chanthaburi", "ADM1_TH": "จันทบุรี", "ADM1_PCODE": "TH22", "ADM0_EN": "Thailand", "ADM0_TH": "ประเทศไทย", "ADM0_PCODE": "TH", "date": "2019-02-18", "validOn": "2022-01-22", "validTo": null }, "geometry": { "type": "MultiPolygon", "coordinates": [ [ [ [ 102.080017, 12.675749 ], [ 102.120543, 12.662517 ], [ 102.135433, 12.635852 ], [ 102.11781, 12.622209 ], [ 102.092469, 12.618868 ], [ 102.09371, 12.601932 ], [ 102.078265, 12.590253 ], [ 102.061681, 12.623162 ], [ 102.074807, 12.641708 ], [ 102.066152, 12.644895 ], [ 102.080017, 12.675749 ], [ 102.080017, 12.675749 ] ] ] ] } },
{ "type": "Feature", "properties": { "Shape_Leng": 0.15260978187, "Shape_Area": 0.00055366789, "ADM3_EN": "Chanthanimit", "ADM3_TH": "จันทนิมิต", "ADM3_PCODE": "TH220107", "ADM3_REF": null, "ADM3ALT1EN": null, "ADM3ALT2EN": null, "ADM3ALT1TH": null, "ADM3ALT2TH": null, "ADM2_EN": "Mueang Chanthaburi", "ADM2_TH": "เมืองจันทบุรี", "ADM2_PCODE": "TH2201", "ADM1_EN": "Chanthaburi", "ADM1_TH": "จันทบุรี", "ADM1_PCODE": "TH22", "ADM0_EN": "Thailand", "ADM0_TH": "ประเทศไทย", "ADM0_PCODE": "TH", "date": "2019-02-18", "validOn": "2022-01-22", "validTo": null }, "geometry": { "type": "MultiPolygon", "coordinates": [ [ [ [ 102.133672, 12.633643 ], [ 102.124503, 12.589266 ], [ 102.111972, 12.589307 ], [ 102.11781, 12.622209 ], [ 102.133672, 12.633643 ], [ 102.133672, 12.633643 ] ] ] ] } },
{ "type": "Feature", "properties": { "Shape_Leng": 0.27132399488999998, "Shape_Area": 0.00275694387, "ADM3_EN": "Bang Kacha", "ADM3_TH": "บางกะจะ", "ADM3_PCODE": "TH220108", "ADM3_REF": null, "ADM3ALT1EN": null, "ADM3ALT2EN": null, "ADM3ALT1TH": null, "ADM3ALT2TH": null, "ADM2_EN": "Mueang Chanthaburi", "ADM2_TH": "เมืองจันทบุรี", "ADM2_PCODE": "TH2201", "ADM1_EN": "Chanthaburi", "ADM1_TH": "จันทบุรี", "ADM1_PCODE": "TH22", "ADM0_EN": "Thailand", "ADM0_TH": "ประเทศไทย", "ADM0_PCODE": "TH", "date": "2019-02-18", "validOn": "2022-01-22", "validTo": null }, "geometry": { "type": "MultiPolygon", "coordinates": [ [ [ [ 102.066238, 12.603691 ], [ 102.081614, 12.583269 ], [ 102.073839, 12.562613 ], [ 102.0777, 12.536142 ], [ 102.048056, 12.526785 ], [ 102.023333, 12.5407 ], [ 102.028224, 12.565874 ], [ 102.053532, 12.601329 ], [ 102.066238, 12.603691 ], [ 102.066238, 12.603691 ] ] ] ] } },
{ "type": "Feature", "properties": { "Shape_Leng": 0.33222492095, "Shape_Area": 0.0043466848, "ADM3_EN": "Salaeng", "ADM3_TH": "แสลง", "ADM3_PCODE": "TH220109", "ADM3_REF": null, "ADM3ALT1EN": null, "ADM3ALT2EN": null, "ADM3ALT1TH": null, "ADM3ALT2TH": null, "ADM2_EN": "Mueang Chanthaburi", "ADM2_TH": "เมืองจันทบุรี", "ADM2_PCODE": "TH2201", "ADM1_EN": "Chanthaburi", "ADM1_TH": "จันทบุรี", "ADM1_PCODE": "TH22", "ADM0_EN": "Thailand", "ADM0_TH": "ประเทศไทย", "ADM0_PCODE": "TH", "date": "2019-02-18", "validOn": "2022-01-22", "validTo": null }, "geometry": { "type": "MultiPolygon", "coordinates": [ [ [ [ 102.099265, 12.74274 ], [ 102.122914, 12.723333 ], [ 102.147987, 12.659804 ], [ 102.133437, 12.640461 ], [ 102.120543, 12.662517 ], [ 102.085118, 12.672226 ], [ 102.068142, 12.700063 ], [ 102.080078, 12.733453 ], [ 102.099265, 12.74274 ], [ 102.099265, 12.74274 ] ] ] ] } },
{ "type": "Feature", "properties": { "Shape_Leng": 0.24092394874, "Shape_Area": 0.00161337179, "ADM3_EN": "Nong Bua", "ADM3_TH": "หนองบัว", "ADM3_PCODE": "TH220110", "ADM3_REF": null, "ADM3ALT1EN": null, "ADM3ALT2EN": null, "ADM3ALT1TH": null, "ADM3ALT2TH": null, "ADM2_EN": "Mueang Chanthaburi", "ADM2_TH": "เมืองจันทบุรี", "ADM2_PCODE": "TH2201", "ADM1_EN": "Chanthaburi", "ADM1_TH": "จันทบุรี", "ADM1_PCODE": "TH22", "ADM0_EN": "Thailand", "ADM0_TH": "ประเทศไทย", "ADM0_PCODE": "TH", "date": "2019-02-18", "validOn": "2022-01-22", "validTo": null }, "geometry": { "type": "MultiPolygon", "coordinates": [ [ [ [ 102.131196, 12.563986 ], [ 102.135875, 12.536765 ], [ 102.117256, 12.519432 ], [ 102.106309, 12.526251 ], [ 102.076521, 12.523383 ], [ 102.063562, 12.533486 ], [ 102.096735, 12.549987 ], [ 102.11216, 12.541975 ], [ 102.111474, 12.556197 ], [ 102.131196, 12.563986 ], [ 102.131196, 12.563986 ] ] ] ] } },
{ "type": "Feature", "properties": { "Shape_Leng": 0.29675209032, "Shape_Area": 0.00299982225, "ADM3_EN": "Phlapphla", "ADM3_TH": "พลับพลา", "ADM3_PCODE": "TH220111", "ADM3_REF": null, "ADM3ALT1EN": null, "ADM3ALT2EN": null, "ADM3ALT1TH": null, "ADM3ALT2TH": null, "ADM2_EN": "Mueang Chanthaburi", "ADM2_TH": "เมืองจันทบุรี", "ADM2_PCODE": "TH2201", "ADM1_EN": "Chanthaburi", "ADM1_TH": "จันทบุรี", "ADM1_PCODE": "TH22", "ADM0_EN": "Thailand", "ADM0_TH": "ประเทศไทย", "ADM0_PCODE": "TH", "date": "2019-02-18", "validOn": "2022-01-22", "validTo": null }, "geometry": { "type": "MultiPolygon", "coordinates": [ [ [ [ 102.142891, 12.635704 ], [ 102.198761, 12.615471 ], [ 102.210971, 12.590446 ], [ 102.205484, 12.570199 ], [ 102.17406, 12.582714 ], [ 102.157672, 12.598543 ], [ 102.126164, 12.601241 ], [ 102.135296, 12.633888 ], [ 102.142891, 12.635704 ], [ 102.142891, 12.635704 ] ] ] ] } }
]
}
