{
"type": "FeatureCollection",
"name": "tambon1",
"crs": { "type": "name", "properties": { "name": "urn:ogc:def:crs:OGC:1.3:CRS84" } },
"features": [
{ "type": "Feature", "properties": { "Shape_Leng": 0.29397195557, "Shape_Area": 0.00336251808, "ADM3_EN": "Phra Achan", "ADM3_TH": "พระอาจารย์", "ADM3_PCODE": "TH260401", "ADM3_REF": null, "ADM3ALT1EN": null, "ADM3ALT2EN": null, "ADM3ALT1TH": null, "ADM3ALT2TH": null, "ADM2_EN": "Ongkharak", "ADM2_TH": "องครักษ์", "ADM2_PCODE": "TH2604", "ADM1_EN": "Nakhon Nayok", "ADM1_TH": "นครนายก", "ADM1_PCODE": "TH26", "ADM0_EN": "Thailand", "ADM0_TH": "ประเทศไทย", "ADM0_PCODE": "TH", "date": "2019-02-18", "validOn": "2022-01-22", "validTo": null }, "geometry": { "type": "MultiPolygon", "coordinates": [ [ [ [ 101.068387, 14.000572 ], [ 101.081547, 13.975258 ], [ 101.043479, 13.976541 ], [ 101.022367, 13.97112 ], [ 100.959321, 13.967454 ], [ 100.959346, 13.997021 ], [ 101.018281, 14.000557 ], [ 101.040067, 14.005789 ], [ 101.068387, 14.000572 ], [ 101.068387, 14.000572 ] ] ] ] } },
{ "type": "Feature", "properties": { "Shape_Leng": 0.27311172943000001, "Shape_Area": 0.00356498157, "ADM3_EN": "Bueng San", "ADM3_TH": "บึงศาล", "ADM3_PCODE": "TH260402", "ADM3_REF": null, "ADM3ALT1EN": null, "ADM3ALT2EN": null, "ADM3ALT1TH": null, "ADM3ALT2TH": null, "ADM2_EN": "Ongkharak", "ADM2_TH": "องครักษ์", "ADM2_PCODE": "TH2604", "ADM1_EN": "Nakhon Nayok", "ADM1_TH": "นครนายก", "ADM1_PCODE": "TH26", "ADM0_EN": "Thailand", "ADM0_TH": "ประเทศไทย", "ADM0_PCODE": "TH", "date": "2019-02-18", "validOn": "2022-01-22", "validTo": null }, "geometry": { "type": "MultiPolygon", "coordinates": [ [ [ [ 100.959364, 14.0168 ], [ 100.925049, 14.015786 ], [ 100.914446, 14.006902 ], [ 100.914886, 14.08401 ], [ 100.959726, 14.101115 ], [ 100.959364, 14.0168 ], [ 100.959364, 14.0168 ] ] ] ] } },
{ "type": "Feature", "properties": { "Shape_Leng": 0.35430405849000002, "Shape_Area": 0.00717667607, "ADM3_EN": "Sisa Krabue", "ADM3_TH": "ศีรษะกระบือ", "ADM3_PCODE": "TH260403", "ADM3_REF": null, "ADM3ALT1EN": null, "ADM3ALT2EN": null, "ADM3ALT1TH": null, "ADM3ALT2TH": null, "ADM2_EN": "Ongkharak", "ADM2_TH": "องครักษ์", "ADM2_PCODE": "TH2604", "ADM1_EN": "Nakhon Nayok", "ADM1_TH": "นครนายก", "ADM1_PCODE": "TH26", "ADM0_EN": "Thailand", "ADM0_TH": "ประเทศไทย", "ADM0_PCODE": "TH", "date": "2019-02-18", "validOn": "2022-01-22", "validTo": null }, "geometry": { "type": "MultiPolygon", "coordinates": [ [ [ [ 101.026055, 14.088095 ], [ 101.035533, 14.063362 ], [ 101.065981, 14.005204 ], [ 100.959346, 13.997021 ], [ 100.959506, 14.068712 ], [ 100.98236, 14.088926 ], [ 101.026055, 14.088095 ], [ 101.026055, 14.088095 ] ] ] ] } },
{ "type": "Feature", "properties": { "Shape_Leng": 0.25502193038999998, "Shape_Area": 0.00280730342, "ADM3_EN": "Pho Thaen", "ADM3_TH": "โพธิ์แทน", "ADM3_PCODE": "TH260404", "ADM3_REF": null, "ADM3ALT1EN": null, "ADM3ALT2EN": null, "ADM3ALT1TH": null, "ADM3ALT2TH": null, "ADM2_EN": "Ongkharak", "ADM2_TH": "องครักษ์", "ADM2_PCODE": "TH2604", "ADM1_EN": "Nakhon Nayok", "ADM1_TH": "นครนายก", "ADM1_PCODE": "TH26", "ADM0_EN": "Thailand", "ADM0_TH": "ประเทศไทย", "ADM0_PCODE": "TH", "date": "2019-02-18", "validOn": "2022-01-22", "validTo": null }, "geometry": { "type": "MultiPolygon", "coordinates": [ [ [ [ 100.965265, 14.231493 ], [ 100.992964, 14.206863 ], [ 100.938628, 14.167345 ], [ 100.932798, 14.196839 ], [ 100.913936, 14.209342 ], [ 100.914122, 14.221583 ], [ 100.959331, 14.243061 ], [ 100.965265, 14.231493 ], [ 100.965265, 14.231493 ] ] ] ] } },
{ "type": "Feature", "properties": { "Shape_Leng": 0.48421537056000002, "Shape_Area": 0.00568505242, "ADM3_EN": "Bang Sombun", "ADM3_TH": "บางสมบูรณ์", "ADM3_PCODE": "TH260405", "ADM3_REF": null, "ADM3ALT1EN": null, "ADM3ALT2EN": null, "ADM3ALT1TH": null, "ADM3ALT2TH": null, "ADM2_EN": "Ongkharak", "ADM2_TH": "องครักษ์", "ADM2_PCODE": "TH2604", "ADM1_EN": "Nakhon Nayok", "ADM1_TH": "นครนายก", "ADM1_PCODE": "TH26", "ADM0_EN": "Thailand", "ADM0_TH": "ประเทศไทย", "ADM0_PCODE": "TH", "date": "2019-02-18", "validOn": "2022-01-22", "validTo": null }, "geometry": { "type": "MultiPolygon", "coordinates": [ [ [ [ 101.111426, 14.061066 ], [ 101.122729, 14.052682 ], [ 101.151788, 14.011582 ], [ 101.172507, 14.012258 ], [ 101.165651, 14.002169 ], [ 101.139236, 14.00149 ], [ 101.1378, 13.969888 ], [ 101.081547, 13.975258 ], [ 101.075253, 13.987465 ], [ 101.085488, 14.000345 ], [ 101.080413, 14.045351 ], [ 101.091545, 14.070137 ], [ 101.089287, 14.089791 ], [ 101.102016, 14.102719 ], [ 101.111449, 14.090818 ], [ 101.111426, 14.061066 ], [ 101.111426, 14.061066 ] ] ] ] } },
{ "type": "Feature", "properties": { "Shape_Leng": 0.34609164449000002, "Shape_Area": 0.00426162887, "ADM3_EN": "Sai Mun", "ADM3_TH": "ทรายมูล", "ADM3_PCODE": "TH260406", "ADM3_REF": null, "ADM3ALT1EN": null, "ADM3ALT2EN": null, "ADM3ALT1TH": null, "ADM3ALT2TH": null, "ADM2_EN": "Ongkharak", "ADM2_TH": "องครักษ์", "ADM2_PCODE": "TH2604", "ADM1_EN": "Nakhon Nayok", "ADM1_TH": "นครนายก", "ADM1_PCODE": "TH26", "ADM0_EN": "Thailand", "ADM0_TH": "ประเทศไทย", "ADM0_PCODE": "TH", "date": "2019-02-18", "validOn": "2022-01-22", "validTo": null }, "geometry": { "type": "MultiPolygon", "coordinates": [ [ [ [ 101.033786, 14.164409 ], [ 101.05105, 14.132415 ], [ 101.066436, 14.147071 ], [ 101.096598, 14.109492 ], [ 101.041772, 14.094066 ], [ 101.018074, 14.121296 ], [ 101.001735, 14.12409 ], [ 100.984516, 14.146831 ], [ 101.029187, 14.178631 ], [ 101.033786, 14.164409 ], [ 101.033786, 14.164409 ] ] ] ] } },
{ "type": "Feature", "properties": { "Shape_Leng": 0.40226067886, "Shape_Area": 0.0053152571, "ADM3_EN": "Bang Pla Kot", "ADM3_TH": "บางปลากด", "ADM3_PCODE": "TH260407", "ADM3_REF": null, "ADM3ALT1EN": null, "ADM3ALT2EN": null, "ADM3ALT1TH": null, "ADM3ALT2TH": null, "ADM2_EN": "Ongkharak", "ADM2_TH": "องครักษ์", "ADM2_PCODE": "TH2604", "ADM1_EN": "Nakhon Nayok", "ADM1_TH": "นครนายก", "ADM1_PCODE": "TH26", "ADM0_EN": "Thailand", "ADM0_TH": "ประเทศไทย", "ADM0_PCODE": "TH", "date": "2019-02-18", "validOn": "2022-01-22", "validTo": null }, "geometry": { "type": "MultiPolygon", "coordinates": [ [ [ [ 100.922964, 14.200068 ], [ 100.932798, 14.196839 ], [ 100.938628, 14.167345 ], [ 100.991996, 14.206112 ], [ 101.028685, 14.178248 ], [ 100.984054, 14.146446 ], [ 100.943277, 14.125963 ], [ 100.913625, 14.135476 ], [ 100.913936, 14.209342 ], [ 100.922964, 14.200068 ], [ 100.922964, 14.200068 ] ] ] ] } },
{ "type": "Feature", "properties": { "Shape_Leng": 0.37907586822, "Shape_Area": 0.00424069757, "ADM3_EN": "Bang Luk Suea", "ADM3_TH": "บางลูกเสือ", "ADM3_PCODE": "TH260408", "ADM3_REF": null, "ADM3ALT1EN": null, "ADM3ALT2EN": null, "ADM3ALT1TH": null, "ADM3ALT2TH": null, "ADM2_EN": "Ongkharak", "ADM2_TH": "องครักษ์", "ADM2_PCODE": "TH2604", "ADM1_EN": "Nakhon Nayok", "ADM1_TH": "นครนายก", "ADM1_PCODE": "TH26", "ADM0_EN": "Thailand", "ADM0_TH": "ประเทศไทย", "ADM0_PCODE": "TH", "date": "2019-02-18", "validOn": "2022-01-22", "validTo": null }, "geometry": { "type": "MultiPolygon", "coordinates": [ [ [ [ 101.101681, 14.101625 ], [ 101.089287, 14.089791 ], [ 101.091545, 14.070137 ], [ 101.080413, 14.045351 ], [ 101.085488, 14.000345 ], [ 101.075253, 13.987465 ], [ 101.031699, 14.075034 ], [ 101.05096, 14.086056 ], [ 101.04489, 14.095064 ], [ 101.096598, 14.109492 ], [ 101.101681, 14.101625 ], [ 101.101681, 14.101625 ] ] ] ] } },
{ "type": "Feature", "properties": { "Shape_Leng": 0.28397437429, "Shape_Area": 0.00205062499, "ADM3_EN": "Ongkharak", "ADM3_TH": "องครักษ์", "ADM3_PCODE": "TH260409", "ADM3_REF": null, "ADM3ALT1EN": null, "ADM3ALT2EN": null, "ADM3ALT1TH": null, "ADM3ALT2TH": null, "ADM2_EN": "Ongkharak", "ADM2_TH": "องครักษ์", "ADM2_PCODE": "TH2604", "ADM1_EN": "Nakhon Nayok", "ADM1_TH": "นครนายก", "ADM1_PCODE": "TH26", "ADM0_EN": "Thailand", "ADM0_TH": "ประเทศไทย", "ADM0_PCODE": "TH", "date": "2019-02-18", "validOn": "2022-01-22", "validTo": null }, "geometry": { "type": "MultiPolygon", "coordinates": [ [ [ [ 101.018254, 14.120162 ], [ 101.034137, 14.096467 ], [ 101.05096, 14.086056 ], [ 101.031699, 14.075034 ], [ 101.025304, 14.09074 ], [ 100.98236, 14.088926 ], [ 100.975463, 14.10865 ], [ 101.007336, 14.127186 ], [ 101.018254, 14.120162 ], [ 101.018254, 14.120162 ] ] ] ] } },
{ "type": "Feature", "properties": { "Shape_Leng": 0.19307386934000001, "Shape_Area": 0.00216330707, "ADM3_EN": "Chumphon", "ADM3_TH": "ชุมพล", "ADM3_PCODE": "TH260410", "ADM3_REF": null, "ADM3ALT1EN": null, "ADM3ALT2EN": null, "ADM3ALT1TH": null, "ADM3ALT2TH": null, "ADM2_EN": "Ongkharak", "ADM2_TH": "องครักษ์", "ADM2_PCODE": "TH2604", "ADM1_EN": "Nakhon Nayok", "ADM1_TH": "นครนายก", "ADM1_PCODE": "TH26", "ADM0_EN": "Thailand", "ADM0_TH": "ประเทศไทย", "ADM0_PCODE": "TH", "date": "2019-02-18", "validOn": "2022-01-22", "validTo": null }, "geometry": { "type": "MultiPolygon", "coordinates": [ [ [ [ 100.936307, 14.015576 ], [ 100.959365, 14.011387 ], [ 100.959321, 13.967454 ], [ 100.914218, 13.961278 ], [ 100.914446, 14.006902 ], [ 100.936307, 14.015576 ], [ 100.936307, 14.015576 ] ] ] ] } },
{ "type": "Feature", "properties": { "Shape_Leng": 0.34897085116999998, "Shape_Area": 0.00331084777, "ADM3_EN": "Khlong Yai", "ADM3_TH": "คลองใหญ่", "ADM3_PCODE": "TH260411", "ADM3_REF": null, "ADM3ALT1EN": null, "ADM3ALT2EN": null, "ADM3ALT1TH": null, "ADM3ALT2TH": null, "ADM2_EN": "Ongkharak", "ADM2_TH": "องครักษ์", "ADM2_PCODE": "TH2604", "ADM1_EN": "Nakhon Nayok", "ADM1_TH": "นครนายก", "ADM1_PCODE": "TH26", "ADM0_EN": "Thailand", "ADM0_TH": "ประเทศไทย", "ADM0_PCODE": "TH", "date": "2019-02-18", "validOn": "2022-01-22", "validTo": null }, "geometry": { "type": "MultiPolygon", "coordinates": [ [ [ [ 100.995545, 14.12557 ], [ 100.975463, 14.10865 ], [ 100.980715, 14.094771 ], [ 100.959506, 14.068712 ], [ 100.959726, 14.101115 ], [ 100.914886, 14.08401 ], [ 100.913625, 14.135476 ], [ 100.943277, 14.125963 ], [ 100.984516, 14.146831 ], [ 100.995545, 14.12557 ], [ 100.995545, 14.12557 ] ] ] ] } }
]
}
